examples/__init__.py
performance_testing/__init__.py
performance_testing/valcheck_performance_testing.py
tests/__init__.py
tests/test_decorators.py
tests/test_fields.py
tests/test_json_serializer.py
tests/test_model_validator.py
tests/test_utils.py
tests/test_validators.py
valcheck/__init__.py
valcheck/decorators.py
valcheck/exceptions.py
valcheck/fields.py
valcheck/meta_classes.py
valcheck/models.py
valcheck/utils.py
valcheck/validators.py
valcheck/apis/__init__.py
valcheck/apis/exceptions.py
valcheck/apis/status_codes.py
valcheck/apis/validators.py
valcheck/serializers/__init__.py
valcheck/serializers/json_serializers.py
valcheck-6.0.dist-info/LICENSE
valcheck-6.0.dist-info/METADATA
valcheck-6.0.dist-info/WHEEL
valcheck-6.0.dist-info/top_level.txt
valcheck-6.0.dist-info/RECORD
