Metadata-Version: 2.1
Name: valcheck
Version: 6.0
Summary: Package for quick data validation (in Python)
Home-page: https://github.com/Nishant173/valcheck
Author: Nishant Rao
Author-email: nishant.rao173@gmail.com
License: MIT
Classifier: Development Status :: 5 - Production/Stable
Classifier: Intended Audience :: Developers
Classifier: License :: OSI Approved :: ISC License (ISCL)
Classifier: Natural Language :: English
Classifier: Programming Language :: Python :: 3.7
Classifier: Operating System :: Unix
Classifier: Operating System :: MacOS :: MacOS X
Classifier: Operating System :: Microsoft :: Windows
License-File: LICENSE
